rename_tools/__init__.py
rename_tools/__main__.py
rename_tools/functions.py
rename_tools-0.0.2.dist-info/METADATA
rename_tools-0.0.2.dist-info/WHEEL
rename_tools-0.0.2.dist-info/entry_points.txt
rename_tools-0.0.2.dist-info/top_level.txt
rename_tools-0.0.2.dist-info/RECORD
