Metadata-Version: 2.1
Name: rename-tools
Version: 0.0.2
Summary: This project provide tools to rename folders and files.
Home-page: UNKNOWN
Author: Thiago Nepomuceno
Author-email: thiago@neps.academy
License: UNKNOWN
Platform: UNKNOWN
Classifier: Programming Language :: Python :: 3
Classifier: License :: OSI Approved :: MIT License
Classifier: Operating System :: OS Independent
Requires-Dist: click
Requires-Dist: rich
